{"oto":"19E", "duraklar":[{"lat":41.00501,"lng":29.02139,"sira":72, "kod":225572,"ad":"NUMUNE HASTANESİ"},{"lat":41.00192,"lng":29.022718,"sira":73, "kod":213701,"ad":"HAYDARPAŞA TEK.L."},{"lat":40.9951,"lng":29.02453,"sira":74, "kod":225542,"ad":"HAMZA YERLİKAYA"},{"lat":40.99242,"lng":29.02427,"sira":75, "kod":404031,"ad":"KADIKÖY"},{"lat":41.00514,"lng":29.2542,"sira":1, "kod":402081,"ad":"YENİDOĞAN PERONLAR"},{"lat":41.00493,"lng":29.25682,"sira":2, "kod":216101,"ad":"MERVE CADDESİ"},{"lat":41.00724,"lng":29.25923,"sira":3, "kod":216822,"ad":"SEÇKİN SOKAK"},{"lat":41.0104,"lng":29.25929,"sira":4, "kod":216832,"ad":"ADAY SOKAK"},{"lat":41.01295,"lng":29.25937,"sira":5, "kod":229812,"ad":"OTLUKBELİ CADDESİ"},{"lat":41.01418,"lng":29.25887,"sira":6, "kod":216842,"ad":"FİLİZ SOKAK"},{"lat":41.01626,"lng":29.25781,"sira":7, "kod":217741,"ad":"KARAPINAR SOKAK"},{"lat":41.0179,"lng":29.2578,"sira":8, "kod":215932,"ad":"VEYSEL KARANİ CAD."},{"lat":41.01891,"lng":29.25581,"sira":9, "kod":215922,"ad":"YUNUS EMRE MAHALLESİ"},{"lat":41.01965,"lng":29.25349,"sira":10, "kod":215912,"ad":"GAMZE SOKAK"},{"lat":41.01911,"lng":29.25026,"sira":11, "kod":215902,"ad":"ABİTLER"},{"lat":41.01666,"lng":29.24889,"sira":12, "kod":215892,"ad":"DOLUNAY SOKAK"},{"lat":41.01394,"lng":29.24557,"sira":13, "kod":216171,"ad":"HÜSEYİN T.SİPAHİ İÖO"},{"lat":41.01025,"lng":29.24277,"sira":14, "kod":216812,"ad":"UMUT SOKAK"},{"lat":41.00827,"lng":29.24033,"sira":15, "kod":216071,"ad":"MERVE MAHALLESİ"},{"lat":41.00858,"lng":29.23676,"sira":16, "kod":216061,"ad":"ÇAMLIKTEPE"},{"lat":41.00889,"lng":29.23328,"sira":17, "kod":216051,"ad":"İHSAN SOKAK"},{"lat":41.0091,"lng":29.23044,"sira":18, "kod":216041,"ad":"UFUK CADDESİ"},{"lat":41.00878,"lng":29.22452,"sira":19, "kod":216031,"ad":"EBRU SOKAK"},{"lat":41.00853,"lng":29.22058,"sira":20, "kod":216022,"ad":"PAZAR YERİ"},{"lat":41.00824,"lng":29.216297,"sira":21, "kod":218861,"ad":"ATATÜRK CADDESİ"},{"lat":41.00841,"lng":29.2149,"sira":22, "kod":222432,"ad":"SARIGAZİ MERKEZ"},{"lat":41.00975,"lng":29.21212,"sira":23, "kod":218851,"ad":"ESKİ ANKARA CAD."},{"lat":41.00887,"lng":29.20836,"sira":24, "kod":217342,"ad":"SONGÜL SOKAK"},{"lat":41.00839,"lng":29.2037,"sira":25, "kod":217202,"ad":"NAR SOKAK"},{"lat":41.00804,"lng":29.19901,"sira":26, "kod":217162,"ad":"MENEKŞE SOKAK"},{"lat":41.00775,"lng":29.19514,"sira":27, "kod":217192,"ad":"ÖREN SOKAK"},{"lat":41.00748,"lng":29.18883,"sira":28, "kod":217182,"ad":"Ş.ÖĞR.NURGÜLKALE İÖO"},{"lat":41.00761,"lng":29.18529,"sira":29, "kod":200692,"ad":"AKASYA SOKAK"},{"lat":41.00771,"lng":29.18265,"sira":30, "kod":217172,"ad":"BARAJ YOLU"},{"lat":41.00737,"lng":29.17844,"sira":31, "kod":214322,"ad":"SARIGÜL SOKAK"},{"lat":41.00704,"lng":29.17525,"sira":32, "kod":214332,"ad":"ŞEHİT YILMAZ ERCAN"},{"lat":41.00632,"lng":29.17342,"sira":33, "kod":217731,"ad":"YENİDÜNYA SİTESİ"},{"lat":41.00283,"lng":29.16859,"sira":34, "kod":217862,"ad":"KADOSAN"},{"lat":41.00144,"lng":29.1642,"sira":35, "kod":217152,"ad":"İMES C KAPISI"},{"lat":41.00253,"lng":29.16226,"sira":36, "kod":202061,"ad":"İMES CAMİİ"},{"lat":41.00381,"lng":29.16043,"sira":37, "kod":218342,"ad":"İMES A KAPISI"},{"lat":41.00128,"lng":29.15648,"sira":38, "kod":217972,"ad":"İMES BULVARI"},{"lat":40.99958,"lng":29.15545,"sira":39, "kod":201941,"ad":"İMES E KAPISI"},{"lat":40.99695,"lng":29.15492,"sira":40, "kod":214871,"ad":"DUDULLU OTOGAR"},{"lat":40.99257,"lng":29.15313,"sira":41, "kod":226561,"ad":"KEMALPAŞA"},{"lat":40.99082,"lng":29.14982,"sira":42, "kod":213741,"ad":"NECİP FAZIL BULVARI"},{"lat":40.9898,"lng":29.14762,"sira":43, "kod":226481,"ad":"Y.ŞEHİR PAZAR YERİ"},{"lat":40.98818,"lng":29.144293,"sira":44, "kod":226471,"ad":"CEMİLE BESLER OO."},{"lat":40.98714,"lng":29.1403,"sira":45, "kod":226461,"ad":"UYDUKENT"},{"lat":40.98574,"lng":29.13646,"sira":46, "kod":211441,"ad":"GİRNE CADDESİ"},{"lat":40.98626,"lng":29.13434,"sira":47, "kod":211451,"ad":"UYDUKENT SİTESİ"},{"lat":40.98748,"lng":29.13408,"sira":48, "kod":207851,"ad":"3. CADDE"},{"lat":40.99072,"lng":29.13568,"sira":49, "kod":205792,"ad":"TEB ATAŞEHİR AND.LİS"},{"lat":40.99158,"lng":29.13182,"sira":50, "kod":205782,"ad":"ATAŞEHİR SİTELER"},{"lat":40.99261,"lng":29.12789,"sira":51, "kod":205772,"ad":"ATAŞEHİR"},{"lat":40.99304,"lng":29.12308,"sira":52, "kod":205762,"ad":"ATAŞEHİR PLAZALAR"},{"lat":40.99268,"lng":29.11846,"sira":53, "kod":205752,"ad":"A. ATATÜRK MH."},{"lat":40.99175,"lng":29.11414,"sira":54, "kod":205742,"ad":"ATAŞEHİR BULVARI"},{"lat":40.98945,"lng":29.11202,"sira":55, "kod":205732,"ad":"MUSTAFA KANAT CAMİİ"},{"lat":40.98751,"lng":29.1093,"sira":56, "kod":205722,"ad":"SİTELER GİRİŞİ"},{"lat":40.98613,"lng":29.10841,"sira":57, "kod":205712,"ad":"VEDAT GÜNYOL CD."},{"lat":40.98194,"lng":29.10481,"sira":58, "kod":210532,"ad":"ZÜBEYDE HNM.ÖĞRT.EVİ"},{"lat":40.97801,"lng":29.10377,"sira":59, "kod":226361,"ad":"ATAŞEHİR HALİ"},{"lat":40.97576,"lng":29.10221,"sira":60, "kod":226331,"ad":"BAHÇELER YOLU"},{"lat":40.976173,"lng":29.09893,"sira":61, "kod":225651,"ad":"KOZYATAĞI METRO"},{"lat":40.9803,"lng":29.09627,"sira":62, "kod":225641,"ad":"YÜZBEŞEVLER"},{"lat":40.9867,"lng":29.08843,"sira":63, "kod":225631,"ad":"YENİSAHRA"},{"lat":40.9909,"lng":29.07816,"sira":64, "kod":206491,"ad":"HASTANE"},{"lat":40.99343,"lng":29.07172,"sira":65, "kod":225621,"ad":"GÖZTEPE KÖPRÜSÜ"},{"lat":40.9958,"lng":29.06504,"sira":66, "kod":229681,"ad":"İST.MEDENİYET ÜNV."},{"lat":40.99936,"lng":29.055737,"sira":67, "kod":401221,"ad":"UZUNÇAYIR METROBÜS"},{"lat":41.002261,"lng":29.044344,"sira":68, "kod":225602,"ad":"ACIBADEM METRO İST."},{"lat":41.00354,"lng":29.03715,"sira":69, "kod":225562,"ad":"KOŞUYOLU KÖPRÜSÜ"},{"lat":41.00565,"lng":29.02677,"sira":70, "kod":227851,"ad":"İSFALT"},{"lat":41.00664,"lng":29.02121,"sira":71, "kod":207031,"ad":"SELİMİYE TARIM A.M.L"}]}
