{"oto":"89İ", "duraklar":[{"lat":41.05236,"lng":28.762359,"sira":1, "kod":301531,"ad":"K.SULTAN SÜLEYMAN"},{"lat":41.05488,"lng":28.761393,"sira":2, "kod":134021,"ad":"K.S.S.ARAŞT.HAST. GİRİŞ"},{"lat":41.05209,"lng":28.75742,"sira":3, "kod":101681,"ad":"ORTA.MAH."},{"lat":41.047554,"lng":28.75842,"sira":4, "kod":101861,"ad":"HASTANE YOLU"},{"lat":41.04467,"lng":28.75962,"sira":5, "kod":101871,"ad":"KATI ATIK TESİSLERİ"},{"lat":41.0388,"lng":28.76175,"sira":6, "kod":124381,"ad":"NÜKLEER ARAŞTIRMA M."},{"lat":41.03691,"lng":28.76353,"sira":7, "kod":124391,"ad":"KONUT BİRLİK"},{"lat":41.0345,"lng":28.76648,"sira":8, "kod":131731,"ad":"K.EHLİBEYT CAMİİ"},{"lat":41.03333,"lng":28.77019,"sira":9, "kod":124411,"ad":"YENİDOĞAN"},{"lat":41.03401,"lng":28.77444,"sira":10, "kod":132091,"ad":"ŞEHİT MÜNİR ALKAN"},{"lat":41.03422,"lng":28.77849,"sira":11, "kod":130311,"ad":"M.AKİF ERSOY HASTANE"},{"lat":41.0345,"lng":28.78394,"sira":12, "kod":104271,"ad":"AVRUPA KONUTLARI 3"},{"lat":41.03504,"lng":28.786417,"sira":13, "kod":176691,"ad":"HALKALI POLİS MERKEZ"},{"lat":41.03342,"lng":28.791224,"sira":14, "kod":128211,"ad":"HALKALI CAMLIK"},{"lat":41.033,"lng":28.79327,"sira":15, "kod":127171,"ad":"OSMANGAZİ"},{"lat":41.03109,"lng":28.79535,"sira":16, "kod":123061,"ad":"EVLİYA ÇELEBİ"},{"lat":41.02819,"lng":28.79627,"sira":17, "kod":133921,"ad":"İNÖNÜ MAHALLESİ"},{"lat":41.02619,"lng":28.79633,"sira":18, "kod":131211,"ad":"HAKAN CAD"},{"lat":41.02457,"lng":28.79625,"sira":19, "kod":124232,"ad":"PAZAR YOLU"},{"lat":41.02232,"lng":28.79671,"sira":20, "kod":126052,"ad":"HALK PAZARI"},{"lat":41.02019,"lng":28.797232,"sira":21, "kod":124222,"ad":"100. YIL İÖO"},{"lat":41.01922,"lng":28.79775,"sira":22, "kod":104282,"ad":"ULU CAMİİ"},{"lat":41.01627,"lng":28.79746,"sira":23, "kod":124212,"ad":"MASLAKÇEŞME"},{"lat":41.01461,"lng":28.79771,"sira":24, "kod":134002,"ad":"SİTELER"},{"lat":41.01195,"lng":28.79818,"sira":25, "kod":131162,"ad":"KAZIM BEKTAŞ CAMİİ"},{"lat":41.01043,"lng":28.7985,"sira":26, "kod":177111,"ad":"M.ERAVUTMUŞ İÖO."},{"lat":41.01012,"lng":28.79537,"sira":27, "kod":124073,"ad":"BORU SANAYİ"},{"lat":41.00504,"lng":28.7973,"sira":28, "kod":124082,"ad":"SEFAKÖY  MERKEZ"},{"lat":41.000183,"lng":28.796995,"sira":29, "kod":101701,"ad":"AREL ÜNİVERSİTESİ"},{"lat":41.00045,"lng":28.805608,"sira":30, "kod":122631,"ad":"K.ÇEKMECE N. SARAYI"},{"lat":40.994721,"lng":28.815153,"sira":31, "kod":122641,"ad":"FİDANLIK"},{"lat":40.992302,"lng":28.831003,"sira":32, "kod":122651,"ad":"KÜLTÜR ÜNİVERSİTESİ"},{"lat":40.99196,"lng":28.836033,"sira":33, "kod":122661,"ad":"KULELİ"},{"lat":40.99159,"lng":28.84488,"sira":34, "kod":111042,"ad":"ŞİRİNEVLER"},{"lat":40.99316,"lng":28.85811,"sira":35, "kod":111031,"ad":"ÇOCUK SİTESİ"},{"lat":40.99492,"lng":28.86389,"sira":36, "kod":131512,"ad":"BAHÇELİEVLER"},{"lat":40.99622,"lng":28.86768,"sira":37, "kod":111022,"ad":"İNCİRLİ"},{"lat":40.99753,"lng":28.87226,"sira":38, "kod":111012,"ad":"İNCİRLİ (E-5)"},{"lat":41.0002,"lng":28.88169,"sira":39, "kod":121861,"ad":"BAKIRKÖY ADLİYESİ"},{"lat":41.00265,"lng":28.889742,"sira":40, "kod":111002,"ad":"KOCATEPE"},{"lat":41.00825,"lng":28.89885,"sira":41, "kod":110992,"ad":"TINAZTEPE"},{"lat":41.01152,"lng":28.9035,"sira":42, "kod":110982,"ad":"NAKLİYECİLER SİTESİ"},{"lat":41.0154,"lng":28.909674,"sira":43, "kod":108202,"ad":"CEVİZLİBAĞ"},{"lat":41.01896,"lng":28.91893,"sira":44, "kod":105561,"ad":"PANORAMA 1453"},{"lat":41.01698,"lng":28.9294,"sira":45, "kod":105571,"ad":"PAZARTEKKE"},{"lat":41.01582,"lng":28.93173,"sira":46, "kod":105581,"ad":"İSTANBUL TIP FAKÜLTE"},{"lat":41.01331,"lng":28.93687,"sira":47, "kod":105591,"ad":"ÇAPA"},{"lat":41.013,"lng":28.93953,"sira":48, "kod":105693,"ad":"FINDIKZADE"},{"lat":41.01499,"lng":28.94065,"sira":49, "kod":107203,"ad":"OĞUZHAN"},{"lat":41.01379,"lng":28.94457,"sira":50, "kod":107192,"ad":"İSKENDERPAŞA"},{"lat":41.012146,"lng":28.946731,"sira":51, "kod":301181,"ad":"AKSARAY PERON"}]}
